[
    {"element": "Stakeholder", "layer": "Motivation", "color": "#CCCCFF"},
    {"element": "Driver", "layer": "Motivation", "color": "#CCCCFF"},
    {"element": "Assessment", "layer": "Motivation", "color": "#CCCCFF"},
    {"element": "Goal", "layer": "Motivation", "color": "#CCCCFF"},
    {"element": "Outcome", "layer": "Motivation", "color": "#CCCCFF"},
    {"element": "Principle", "layer": "Motivation", "color": "#CCCCFF"},
    {"element": "Requirement", "layer": "Motivation", "color": "#CCCCFF"},
    {"element": "Constraint", "layer": "Motivation", "color": "#CCCCFF"},
    {"element": "Meaning", "layer": "Motivation", "color": "#CCCCFF"},
    {"element": "Value", "layer": "Motivation", "color": "#CCCCFF"},
    {"element": "Resource", "layer": "Strategy", "color": "#F5DEAA"},
    {"element": "Capability", "layer": "Strategy", "color": "#F5DEAA"},
    {"element": "Value Stream", "layer": "Strategy", "color": "#F5DEAA"},
    {"element": "Course of Action", "layer": "Strategy", "color": "#F5DEAA"},
    {"element": "Business Actor", "layer": "Business", "color": "#FFFFAE"},
    {"element": "Business Role", "layer": "Business", "color": "#FFFFAE"},
    {"element": "Business Collaboration", "layer": "Business", "color": "#FFFFAE"},
    {"element": "Business Interface", "layer": "Business", "color": "#FFFFAE"},
    {"element": "Business Process", "layer": "Business", "color": "#FFFFAE"},
    {"element": "Business Function", "layer": "Business", "color": "#FFFFAE"},
    {"element": "Business Interaction", "layer": "Business", "color": "#FFFFAE"},
    {"element": "Business Event", "layer": "Business", "color": "#FFFFAE"},
    {"element": "Business Service", "layer": "Business", "color": "#FFFFAE"},
    {"element": "Business Object", "layer": "Business", "color": "#FFFFAE"},
    {"element": "Contract", "layer": "Business", "color": "#FFFFAE"},
    {"element": "Representation", "layer": "Business", "color": "#FFFFAE"},
    {"element": "Product", "layer": "Business", "color": "#FFFFAE"},
    {"element": "Application Component", "layer": "Application", "color": "#AEFFFF"},
    {"element": "Application Collaboration", "layer": "Application", "color": "#AEFFFF"},
    {"element": "Application Interface", "layer": "Application", "color": "#AEFFFF"},
    {"element": "Application Function", "layer": "Application", "color": "#AEFFFF"},
    {"element": "Application Interaction", "layer": "Application", "color": "#AEFFFF"},
    {"element": "Application Process", "layer": "Application", "color": "#AEFFFF"},
    {"element": "Application Event", "layer": "Application", "color": "#AEFFFF"},
    {"element": "Application Service", "layer": "Application", "color": "#AEFFFF"},
    {"element": "Data Object", "layer": "Application", "color": "#AEFFFF"},
    {"element": "Node", "layer": "Technology", "color": "#AEFFAE"},
    {"element": "Device", "layer": "Technology", "color": "#AEFFAE"},
    {"element": "System Software", "layer": "Technology", "color": "#AEFFAE"},
    {"element": "Technology Collaboration", "layer": "Technology", "color": "#AEFFAE"},
    {"element": "Technology Interface", "layer": "Technology", "color": "#AEFFAE"},
    {"element": "Path", "layer": "Technology", "color": "#AEFFAE"},
    {"element": "Communication Network", "layer": "Technology", "color": "#AEFFAE"},
    {"element": "Technology Function", "layer": "Technology", "color": "#AEFFAE"},
    {"element": "Technology Process", "layer": "Technology", "color": "#AEFFAE"},
    {"element": "Technology Interaction", "layer": "Technology", "color": "#AEFFAE"},
    {"element": "Technology Event", "layer": "Technology", "color": "#AEFFAE"},
    {"element": "Technology Service", "layer": "Technology", "color": "#AEFFAE"},
    {"element": "Artifact", "layer": "Technology", "color": "#AEFFAE"},
    {"element": "Equipment", "layer": "Technology", "color": "#AEFFAE"},
    {"element": "Facility", "layer": "Technology", "color": "#AEFFAE"},
    {"element": "Distribution Network", "layer": "Technology", "color": "#AEFFAE"},
    {"element": "Material", "layer": "Technology", "color": "#AEFFAE"},
    {"element": "Work Package", "layer": "Implementation and Migration", "color": "#FFDFDF"},
    {"element": "Deliverable", "layer": "Implementation and Migration", "color": "#FFDFDF"},
    {"element": "Implementation Event", "layer": "Implementation and Migration", "color": "#FFDFDF"},
    {"element": "Plateau", "layer": "Implementation and Migration", "color": "#FFDFDF"},
    {"element": "Gap", "layer": "Implementation and Migration", "color": "#FFDFDF"},
    {"element": "Grouping", "layer": "Composite", "color": "#EED1E3"},
    {"element": "Location", "layer": "Composite", "color": "#EED1E3"}
  ]
  